kb_controller/.DS_Store
kb_controller/__init__.py
kb_controller/controller.py
kb_controller/ubitemulator.py
kb_controller/helpers/__init__.py
kb_controller/helpers/event_poller.py
kb_controller/helpers/helper.py
kb_controller/helpers/kb_central.py
kb_controller/helpers/kb_config.py
kb_controller/helpers/kbc-default-config.ini
kb_controller/helpers/microbit.py
kb_controller-1.0.1.dist-info/METADATA
kb_controller-1.0.1.dist-info/WHEEL
kb_controller-1.0.1.dist-info/licenses/LICENSE
kb_controller-1.0.1.dist-info/RECORD
