Metadata-Version: 2.1
Name: kb_controller
Version: 1.0.1
Summary: CPVB Kuglebane Controller - forår 2023
Project-URL: Homepage, https://github.com/Coding-Pirates-Viborg/kuglebane-controller
Project-URL: Bug Tracker, https://github.com/Coding-Pirates-Viborg/kuglebane-controller/issues
Author-email: esgem <esge@kodepirat.dk>
License-File: LICENSE
Classifier: License :: OSI Approved :: MIT License
Classifier: Operating System :: OS Independent
Classifier: Programming Language :: Python :: 3
Requires-Python: >=3.7
Requires-Dist: pyjwt
Requires-Dist: pyserial
Requires-Dist: requests
